setup.py
shinkenplugins/__init__.py
shinkenplugins.plugins.arp_no_change.egg-info/PKG-INFO
shinkenplugins.plugins.arp_no_change.egg-info/SOURCES.txt
shinkenplugins.plugins.arp_no_change.egg-info/dependency_links.txt
shinkenplugins.plugins.arp_no_change.egg-info/entry_points.txt
shinkenplugins.plugins.arp_no_change.egg-info/namespace_packages.txt
shinkenplugins.plugins.arp_no_change.egg-info/requires.txt
shinkenplugins.plugins.arp_no_change.egg-info/top_level.txt
shinkenplugins/plugins/__init__.py
shinkenplugins/plugins/arp_no_change/__init__.py
shinkenplugins/plugins/arp_no_change/arp_no_change.py
shinkenplugins/plugins/arp_no_change/arp_no_change_low_level.py