Metadata-Version: 1.0
Name: shinkenplugins.plugins.arp-no-change
Version: 1.2
Summary: Check ARP address do not change
Home-page: https://github.com/savoirfairelinux/sfl-shinken-plugins
Author: Savoir-faire Linux
Author-email: supervision@savoirfairelinux.com
License: GPL3+
Platform: any
